odoo/addons/web_group_expand/README.rst
odoo/addons/web_group_expand/__init__.py
odoo/addons/web_group_expand/__manifest__.py
odoo/addons/web_group_expand/i18n/web_group_expand.pot
odoo/addons/web_group_expand/readme/CONTRIBUTORS.rst
odoo/addons/web_group_expand/readme/DESCRIPTION.rst
odoo/addons/web_group_expand/static/description/icon.png
odoo/addons/web_group_expand/static/description/index.html
odoo/addons/web_group_expand/static/src/js/web_group_expand.js
odoo/addons/web_group_expand/static/src/js/web_group_expand_menu.js
odoo/addons/web_group_expand/static/src/less/web_group_expand.less
odoo/addons/web_group_expand/static/src/xml/web_group_expand.xml
odoo/addons/web_group_expand/templates/assets.xml
odoo11_addon_web_group_expand-11.0.1.0.2.dist-info/METADATA
odoo11_addon_web_group_expand-11.0.1.0.2.dist-info/WHEEL
odoo11_addon_web_group_expand-11.0.1.0.2.dist-info/top_level.txt
odoo11_addon_web_group_expand-11.0.1.0.2.dist-info/RECORD
